[
  {
    "title": "free",
    "subtitle": "anyone can host",
    "description": "You can to host Tournament and make your own community and bring them the esports experience."
  },
  {
    "title": "80%",
    "subtitle": "Increase Efficency",
    "description": "Decrease your Esports tournament host cost by 70% and manage your budget efficiency."
  },
  {
    "title": "70%",
    "subtitle": "Decrease Cost",
    "description": "Decrease your Esports tournament host cost by 70% and manage your budget efficiency."
  },
  {
    "title": "10X",
    "subtitle": "Higher Visibility",
    "description": "Increase your Esports and Gaming visibility by hosting a professional esports tournament at top in class level"
  },
  {
    "title": "25K",
    "subtitle": "Interactional elements",
    "description": "Our Experienced Team Has hosted over 200+ Esports events and 80+ Analysis, Case studies to tailor this."
  }
]
